envoke/__init__.py
envoke/core.py
envoke-0.3.1.dist-info/LICENSE
envoke-0.3.1.dist-info/METADATA
envoke-0.3.1.dist-info/WHEEL
envoke-0.3.1.dist-info/top_level.txt
envoke-0.3.1.dist-info/RECORD
