Metadata-Version: 2.1
Name: envoke
Version: 0.3.1
Summary: the python macro package
Author-email: Kian McKenna <kian@mckenna.cloud>
License: MIT License
Project-URL: Homepage, https://github.com/cowboycodr/envoke
Project-URL: Repository, https://github.com/cowboycodr/envoke
Keywords: macro,keyboard,input,automation
Classifier: License :: OSI Approved :: MIT License
Classifier: Programming Language :: Python
Classifier: Programming Language :: Python :: 3
Requires-Python: >=3.6
License-File: LICENSE
Requires-Dist: pyautogui ==0.9.54
Provides-Extra: dev
Requires-Dist: black ; extra == 'dev'
Requires-Dist: bumpver ; extra == 'dev'
Requires-Dist: isort ; extra == 'dev'
Requires-Dist: pip-tools ; extra == 'dev'
Requires-Dist: pytest ; extra == 'dev'
